kanna/__init__.py
kanna/commands/list.py
kanna/commands/task_runner.py
kanna/core/interfaces/renderer.py
kanna/renderers/__init__.py
kanna/renderers/dot.py
kanna/renderers/shell.py
kanna/utils/__init__.py
kanna/utils/arguments.py
kanna/utils/colors.py
kanna/utils/outputs.py
kanna/utils/project.py
kanna-0.5.1.dist-info/METADATA
kanna-0.5.1.dist-info/WHEEL
kanna-0.5.1.dist-info/entry_points.txt
kanna-0.5.1.dist-info/RECORD
