Metadata-Version: 2.4
Name: kanna
Version: 0.5.1
Summary: A task runner for pyproject environments
Project-URL: Homepage, https://github.com/alexandresenpai/kanna
Project-URL: Repository, https://github.com/alexandresenpai/kanna
Author-email: AlexandreSenpai <alexandrebsramos@hotmail.com>
License: MIT
Classifier: License :: OSI Approved :: MIT License
Classifier: Operating System :: OS Independent
Classifier: Programming Language :: Python :: 3
Requires-Python: >=3.12
Requires-Dist: python-dotenv>=1.1.0
Requires-Dist: tomli>=2.2.1
